fling_cli/__init__.py
fling_cli/auth.py
fling_cli/bin/__init__.py
fling_cli/bin/fling.py
fling_cli/certbot_fling_plugin.py
fling_cli/logo-hc.txt
fling_cli-0.1.7.dist-info/METADATA
fling_cli-0.1.7.dist-info/WHEEL
fling_cli-0.1.7.dist-info/entry_points.txt
fling_cli-0.1.7.dist-info/RECORD
