Metadata-Version: 2.1
Name: fling-cli
Version: 0.1.7
Summary: Side Project Management from the command line
Author: Joshua McKenty
Author-email: jmckenty@gmail.com
Requires-Python: >=3.9,<4.0
Classifier: Programming Language :: Python :: 3
Classifier: Programming Language :: Python :: 3.9
Classifier: Programming Language :: Python :: 3.10
Classifier: Programming Language :: Python :: 3.11
Requires-Dist: certbot
Requires-Dist: click
Requires-Dist: cookiecutter
Requires-Dist: fastapi (>=0.95.0,<0.96.0)
Requires-Dist: fling-client (>=0.1.3,<0.2.0)
Requires-Dist: fling-core
Requires-Dist: gitpython (>=3.1.31,<4.0.0)
Requires-Dist: giturlparse (>=0.10.0,<0.11.0)
Requires-Dist: keyring (>=23.13.1,<24.0.0)
Requires-Dist: python-dotenv
Requires-Dist: python-git-info (>=0.8.2,<0.9.0)
Requires-Dist: requests-oauthlib (>=1.3.1,<2.0.0)
Requires-Dist: rich-click
Requires-Dist: uvicorn (>=0.21.1,<0.22.0)
